magpylib_force/__init__.py
magpylib_force/force.py
magpylib_force/meshing.py
magpylib_force/utility.py
tests/__init__.py
tests/test_FEM.py
tests/test_basics.py
tests/test_interface.py
tests/test_meshing.py
tests/test_physics.py
tests/test_self_consistency.py
magpylib_force-0.3.1.dist-info/LICENSE
magpylib_force-0.3.1.dist-info/METADATA
magpylib_force-0.3.1.dist-info/WHEEL
magpylib_force-0.3.1.dist-info/top_level.txt
magpylib_force-0.3.1.dist-info/RECORD
