Metadata-Version: 2.1
Name: magpylib-force
Version: 0.3.1
Summary: An extension to the Magpylib library, providing force computation
Home-page: https://github.com/magpylib/magpylib-force
Author: Magpylib
Author-email: magpylib@gmail.com
License: MIT
Classifier: Development Status :: 2 - Pre-Alpha
Classifier: License :: OSI Approved :: BSD License
Classifier: Programming Language :: Python :: 3
Classifier: Topic :: Software Development :: Libraries :: Python Modules
License-File: LICENSE
Requires-Dist: magpylib>=5.0.1
